__init__.py
tdrawer.py
tdrawer/__init__.py
tdrawer/_tdrawer.cp37-win_amd64.pyd
tdrawer/glfw3.dll
tdrawer/tdrawer.py
tdrawer-0.0.1.dist-info/METADATA
tdrawer-0.0.1.dist-info/WHEEL
tdrawer-0.0.1.dist-info/top_level.txt
tdrawer-0.0.1.dist-info/RECORD
