Metadata-Version: 2.1
Name: tdrawer
Version: 0.0.1
Summary: A simple OpenGL drawer
Home-page: UNKNOWN
Author: Terry Qi
License: UNKNOWN
Platform: UNKNOWN
Requires-Python: >=3.7
Requires-Dist: cffi
